README.md
setup.py
jetstreamer/__init__.py
jetstreamer/__main__.py
jetstreamer/pipeline.py
jetstreamer.egg-info/PKG-INFO
jetstreamer.egg-info/SOURCES.txt
jetstreamer.egg-info/dependency_links.txt
jetstreamer.egg-info/entry_points.txt
jetstreamer.egg-info/top_level.txt