Metadata-Version: 2.1
Name: jetstreamer
Version: 0.0.3
Summary: Image and inference metadata recording utility for NVIDIA Tegra
Home-page: UNKNOWN
Author: Michael de Gans
License: UNKNOWN
Project-URL: Bug Reports, https://github.com/mdegans/jetstreamer/issues
Project-URL: Source, https://github.com/mdegans/jetstreamer/
Platform: UNKNOWN
Classifier: Development Status :: 3 - Alpha
Classifier: Intended Audience :: End Users/Desktop
Classifier: Intended Audience :: Developers
Classifier: Topic :: Scientific/Engineering :: Artificial Intelligence
Classifier: Topic :: Scientific/Engineering :: Image Recognition
Classifier: License :: OSI Approved :: MIT License
Classifier: Programming Language :: Python :: 3
Classifier: Programming Language :: Python :: 3.6
Classifier: Programming Language :: Python :: 3.7
Classifier: Programming Language :: Python :: 3.8
Requires-Python: >=3.6
